django_fullclean/__init__.py
django_fullclean-0.0.5.dist-info/LICENSE.txt
django_fullclean-0.0.5.dist-info/METADATA
django_fullclean-0.0.5.dist-info/WHEEL
django_fullclean-0.0.5.dist-info/top_level.txt
django_fullclean-0.0.5.dist-info/RECORD
