Metadata-Version: 1.1
Name: django-fullclean
Version: 0.0.5
Summary: Force django model call full_clean before save.
Home-page: https://github.com/fish-ball/django-fullclean
Author: Alfred Huang
Author-email: 57082212@qq.com
License: MIT License
Download-URL: https://github.com/fish-ball/django-fullclean/tarball/0.0.5
Keywords: django,model,validator,full_clean
Platform: any
